{
  "total_loc": 1368,
  "max_loc_per_batch": 2000,
  "batches": [
    {
      "batch_id": 1,
      "files": [
        "PULL_REQUEST.md",
        "QUICKSTART.md",
        "README.md",
        "STARTUP_GUIDE.md",
        "app/__init__.py",
        "app/blueprints/api/market_routes.py",
        "app/config.py",
        "app/integrations/free_gold_api_client.py",
        "app/integrations/polygon_client.py",
        "app/integrations/twelvedata_client.py",
        "app/services/gold_service.py",
        "app/services/market_prediction_service.py",
        "app/static/css/dashboard.css",
        "app/static/js/etf_forecast.js",
        "app/templates/about.html",
        "app/templates/dashboard.html"
      ],
      "loc": 1368,
      "notes": "Single batch (LOC within limit)."
    }
  ],
  "triage_notes": []
}